pyEX/__init__.py
pyEX/_version.py
pyEX/client.py
pyEX/account/__init__.py
pyEX/alternative/__init__.py
pyEX/alternative/alternative.py
pyEX/commodities/__init__.py
pyEX/commodities/commodities.py
pyEX/common/__init__.py
pyEX/common/checks.py
pyEX/common/exception.py
pyEX/common/timing.py
pyEX/common/urls.py
pyEX/cryptocurrency/__init__.py
pyEX/cryptocurrency/cryptocurrency.py
pyEX/economic/__init__.py
pyEX/economic/economic.py
pyEX/files/__init__.py
pyEX/files/files.py
pyEX/fx/__init__.py
pyEX/fx/fx.py
pyEX/markets/__init__.py
pyEX/markets/markets.py
pyEX/metadata/__init__.py
pyEX/options/__init__.py
pyEX/options/options.py
pyEX/points/__init__.py
pyEX/points/points.py
pyEX/premium/__init__.py
pyEX/premium/auditanalytics/__init__.py
pyEX/premium/brain/__init__.py
pyEX/premium/extractalpha/__init__.py
pyEX/premium/fraudfactors/__init__.py
pyEX/premium/kavout/__init__.py
pyEX/premium/newconstructs/__init__.py
pyEX/premium/precisionalpha/__init__.py
pyEX/premium/stocktwits/__init__.py
pyEX/premium/valuengine/__init__.py
pyEX/premium/wallstreethorizon/__init__.py
pyEX/rates/__init__.py
pyEX/rates/rates.py
pyEX/refdata/__init__.py
pyEX/refdata/calendar.py
pyEX/refdata/exchanges.py
pyEX/refdata/figi.py
pyEX/refdata/refdata.py
pyEX/refdata/search.py
pyEX/refdata/sectors.py
pyEX/refdata/symbols.py
pyEX/rules/__init__.py
pyEX/rules/engine.py
pyEX/stats/__init__.py
pyEX/stats/stats.py
pyEX/stocks/__init__.py
pyEX/stocks/batch.py
pyEX/stocks/corporateActions.py
pyEX/stocks/fundamentals.py
pyEX/stocks/iex.py
pyEX/stocks/marketInfo.py
pyEX/stocks/news.py
pyEX/stocks/prices.py
pyEX/stocks/profiles.py
pyEX/stocks/research.py
pyEX/stocks/stocks.py
pyEX/stocks/timeseries.py
pyEX/streaming/__init__.py
pyEX/streaming/cryptocurrency.py
pyEX/streaming/fx.py
pyEX/streaming/news.py
pyEX/streaming/sentiment.py
pyEX/streaming/sse.py
pyEX/streaming/stock.py
pyEX/streaming/ws.py
pyEX/studies/__init__.py
pyEX/studies/peercorrelation.py
pyEX/studies/returns.py
pyEX/studies/utils.py
pyEX-0.5.0.dist-info/AUTHORS
pyEX-0.5.0.dist-info/LICENSE
pyEX-0.5.0.dist-info/METADATA
pyEX-0.5.0.dist-info/WHEEL
pyEX-0.5.0.dist-info/top_level.txt
pyEX-0.5.0.dist-info/RECORD
