Metadata-Version: 2.1
Name: pyEX
Version: 0.5.0
Summary: Rest API to IEX
Home-page: https://github.com/iexcloud/pyEX
Author: Tim Paine
Author-email: t.paine154@gmail.com
License: Apache 2.0
Keywords: finance data
Platform: UNKNOWN
Classifier: Development Status :: 3 - Alpha
Classifier: Programming Language :: Python :: 3
Classifier: Programming Language :: Python :: 3.6
Classifier: Programming Language :: Python :: 3.7
Classifier: Programming Language :: Python :: 3.8
Provides-Extra: dev
Provides-Extra: async
Provides-Extra: studies
